{
  "type": "subcategory",
  "chapterCode": "XIX",
  "chapter": "Injury, poisoning and certain other consequences of external causes",
  "blockCode": "T66-T78",
  "block": "Other and unspecified effects of external causes",
  "categoryCode": "T74",
  "category": "Maltreatment syndromes",
  "subcategory": "T74.1",
  "title": "Physical abuse",
  "inclusion": [
    "Battered: baby or child syndrome NOS",
    "Battered: spouse syndrome NOS"
  ],
  "exclusion": [
    "birth trauma",
    "obstetric trauma",
    "malunion of fracture",
    "nonunion of fracture [pseudarthrosis]",
    "pathological fracture",
    "pathological fracture with osteoporosis",
    "stress fracture"
  ],
  "children": null
}