{
  "type": "subcategory",
  "chapterCode": "XVII",
  "chapter": "Congenital malformations, deformations and chromosomal abnormalities",
  "blockCode": "Q65-Q79",
  "block": "Congenital malformations and deformations of the musculoskeletal system",
  "categoryCode": "Q71",
  "category": "Reduction defects of upper limb",
  "subcategory": "Q71.0",
  "title": "Congenital complete absence of upper limb(s)",
  "inclusion": null,
  "exclusion": [
    "inborn errors of metabolism"
  ],
  "children": null
}