{
  "type": "subcategory",
  "chapterCode": "III",
  "chapter": "Diseases of the blood and blood-forming organs and certain disorders involving the immune mechanism",
  "blockCode": "D60-D64",
  "block": "Aplastic and other anaemias",
  "categoryCode": "D60",
  "category": "Acquired pure red cell aplasia [erythroblastopenia]",
  "subcategory": "D60.9",
  "title": "Acquired pure red cell aplasia, unspecified",
  "inclusion": [
    "red cell aplasia (acquired)(adult)(with thymoma)"
  ],
  "exclusion": [
    "autoimmune disease (systemic) NOS",
    "certain conditions originating in the perinatal period",
    "complications of pregnancy, childbirth and the puerperium",
    "congenital malformations, deformations and chromosomal abnormalities",
    "endocrine, nutritional and metabolic diseases",
    "human immunodeficiency virus [HIV] disease",
    "injury, poisoning and certain other consequences of external causes",
    "neoplasms",
    "symptoms, signs and abnormal clinical and laboratory findings, not elsewhere classified"
  ],
  "children": null
}